Metadata-Version: 2.1
Name: graphene-django-optimizer-reloaded
Version: 0.9.2
Summary: Optimize database access inside graphene queries.
Home-page: https://edugit.org/AlekSIS/libs/graphene-django-optimizer
Author: Jonathan Weth
Author-email: dev@jonathanweth.de
License: MIT
Keywords: graphene django optimizer optimize graphql query prefetch select related
Classifier: Development Status :: 4 - Beta
Classifier: Environment :: Web Environment
Classifier: Intended Audience :: Developers
Classifier: License :: OSI Approved :: MIT License
Classifier: Operating System :: OS Independent
Classifier: Programming Language :: Python
Classifier: Programming Language :: Python :: 3
Classifier: Programming Language :: Python :: 3.6
Classifier: Programming Language :: Python :: 3.7
Classifier: Programming Language :: Python :: 3.8
Classifier: Framework :: Django
Classifier: Framework :: Django :: 2.2
Classifier: Framework :: Django :: 3.1
License-File: LICENSE
